setup.py
PyPlato.egg-info/PKG-INFO
PyPlato.egg-info/SOURCES.txt
PyPlato.egg-info/dependency_links.txt
PyPlato.egg-info/requires.txt
PyPlato.egg-info/top_level.txt
bin/plato
src/plato/__init__.py
src/plato/application.py
src/plato/schedule/__init__.py
src/plato/schedule/local.py
src/plato/schedule/lsf.py
src/plato/shell/__init__.py
src/plato/shell/coreutils.py
src/plato/shell/findutils.py