Metadata-Version: 1.0
Name: PyPlato
Version: 0.1.4
Summary: Python Batching Utilities
Home-page: https://github.com/ewiger/plato
Author: Yauhen Yakimovich
Author-email: eugeny.yakimovitch@gmail.com
License: GPL
Download-URL: https://github.com/ewiger/plato/tarball/master
Platform: UNKNOWN
